evidence/__init__.py
evidence/config.py
evidence/manifest.yml
evidence/odm/hit.py
evidence/odm/models/evidence.py
howler_evidence_plugin-0.1.0.125.dist-info/METADATA
howler_evidence_plugin-0.1.0.125.dist-info/WHEEL
howler_evidence_plugin-0.1.0.125.dist-info/entry_points.txt
howler_evidence_plugin-0.1.0.125.dist-info/licenses/LICENSE
howler_evidence_plugin-0.1.0.125.dist-info/RECORD
