Metadata-Version: 2.4
Name: howler-evidence-plugin
Version: 0.1.0.125
Summary: A howler plugin to add additional nested ECS fields to the Howler ODM
License: MIT
License-File: LICENSE
Author: CCCS
Author-email: analysis-development@cyber.gc.ca
Requires-Python: >=3.9.17, <4.0
Classifier: License :: OSI Approved :: MIT License
Classifier: Programming Language :: Python :: 3
Classifier: Programming Language :: Python :: 3.10
Classifier: Programming Language :: Python :: 3.11
Classifier: Programming Language :: Python :: 3.12
Classifier: Programming Language :: Python :: 3.13
Classifier: Programming Language :: Python :: 3.14
